Lab1/dataflow/Lab1_dataflow.v
module	Lab1_dataflow(F, A, B, C, D);

    output F;
    input A, B, C, D;
    wire w1, w2, w3, w4, w5, w6, w7, w8;

    assign w1 = ~D;
    assign w2 = ~B;
    assign w3 = ~A;
    assign w4 = A & w1;
    assign w5 = C & w2;
    assign w6 = w4 | w5;
    assign w7 = C & D;
    assign w8 = w3 | w7;
    assign F = w8 & w6;

endmodule

Lab1/dataflow/t_Lab1_dataflow.v
module	t_Lab1_dataflow;

    wire F;
    reg A, B, C, D;

	//instantiate device under test
    Lab1_dataflow M1(F, A, B, C, D);

	//apply inputs one at a time
	initial	begin
        $dumpfile("Lab1_dataflow.vcd");
        $dumpvars;
        A=1'b0; B=1'b0; C=1'b0; D=1'b0;
        #100 A=1'b0; B=1'b0; C=1'b0;  D=1'b1;
        #100 A=1'b0; B=1'b0; C=1'b1;  D=1'b0;
        #100 A=1'b0; B=1'b0; C=1'b1;  D=1'b1;
        #100 A=1'b0; B=1'b1; C=1'b0;  D=1'b0;
        #100 A=1'b0; B=1'b1; C=1'b0;  D=1'b1;
        #100 A=1'b0; B=1'b1; C=1'b1;  D=1'b0;
        #100 A=1'b0; B=1'b1; C=1'b1;  D=1'b1;
        #100 A=1'b1; B=1'b0; C=1'b0;  D=1'b0;
        #100 A=1'b1; B=1'b0; C=1'b0;  D=1'b1;
        #100 A=1'b1; B=1'b0; C=1'b1;  D=1'b0;
        #100 A=1'b1; B=1'b0; C=1'b1;  D=1'b1;
        #100 A=1'b1; B=1'b1; C=1'b0;  D=1'b0;
        #100 A=1'b1; B=1'b1; C=1'b0;  D=1'b1;
        #100 A=1'b1; B=1'b1; C=1'b1;  D=1'b0;
        #100 A=1'b1; B=1'b1; C=1'b1;  D=1'b1;
    end
    initial #1600 $finish;

endmodule

Lab1/dataflow/Lab1_dataflow.vcd
$date
	Wed May  6 22:38:51 2020
$end
$version
	Icarus Verilog
$end
$timescale
	1s
$end
$scope module t_Lab1_dataflow $end
$var wire 1 ! F $end
$var reg 1 " A $end
$var reg 1 # B $end
$var reg 1 $ C $end
$var reg 1 % D $end
$scope module M1 $end
$var wire 1 " A $end
$var wire 1 # B $end
$var wire 1 $ C $end
$var wire 1 % D $end
$var wire 1 ! F $end
$var wire 1 & w1 $end
$var wire 1 ' w2 $end
$var wire 1 ( w3 $end
$var wire 1 ) w4 $end
$var wire 1 * w5 $end
$var wire 1 + w6 $end
$var wire 1 , w7 $end
$var wire 1 - w8 $end
$upscope $end
$upscope $end
$enddefinitions $end
#0
$dumpvars
1-
0,
0+
0*
0)
1(
1'
1&
0%
0$
0#
0"
0!
$end
#100
0&
1%
#200
1!
1+
1&
1*
0%
1$
#300
0&
1,
1%
#400
0!
0+
1&
0*
0,
0'
0%
0$
1#
#500
0&
1%
#600
1&
0%
1$
#700
0&
1,
1%
#800
1+
1)
0-
1&
0,
1'
0(
0%
0$
0#
1"
#900
0+
0)
0&
1%
#1000
1)
1+
1&
1*
0%
1$
#1100
1!
0)
1-
0&
1,
1%
#1200
0!
1)
1+
0-
1&
0*
0,
0'
0%
0$
1#
#1300
0+
0)
0&
1%
#1400
1+
1)
1&
0%
1$
#1500
0+
0!
0)
1-
0&
1,
1%
