Lab2/Lab2_0719819_游心瑜/Lab2_CLG_dataflow.v
module Lab2_CLG_dataflow(C, P, G, C0);

    output [4:1] C;
    input [3:0] P, G;
    input C0;

    assign C[1] = (P[0] & C0) | G[0];
    assign C[2] = (P[0] & C0 & P[1]) | (P[1] & G[0]) | G[1];
    assign C[3] = (P[0] & C0 & P[1] & P[2]) | (P[1] & G[0] & P[2]) | (G[1] & P[2]) | G[2];
    assign C[4] = (P[0] & C0 & P[1] & P[2] & P[3]) | (P[1] & G[0] & P[2] & P[3]) | (G[1] & P[2] & P[3]) | (G[2] & P[3]) | G[3];

endmodule

Lab2/Lab2_0719819_游心瑜/Lab2_4_bit_CLA.v
module Lab2_4_bit_CLA(output [3:0] Sum, output Cout, input [3:0] A, B, input Cin);

    wire [4:1] C;
    wire [3:0] P, G;

    and G1(G[0], A[0], B[0]);
    xor G2(P[0], A[0], B[0]);

    and G3(G[1], A[1], B[1]);
    xor G4(P[1], A[1], B[1]);

    and G5(G[2], A[2], B[2]);
    xor G6(P[2], A[2], B[2]);

    and G7(G[3], A[3], B[3]);
    xor G8(P[3], A[3], B[3]);

    Lab2_CLG_dataflow M2(C, P, G, Cin);

    xor G9(Sum[0], P[0], Cin);
    xor G10(Sum[1], P[1], C[1]);
    xor G11(Sum[2], P[2], C[2]);
    xor G12(Sum[3], P[3], C[3]);

    assign Cout = C[4];
endmodule

Lab2/Lab2_0719819_游心瑜/t_Lab2_4_bit_CLA.v
module    t_Lab2_4_bit_CLA;

    reg [3:0] A, B;
    reg Cin;

    wire [3:0] Sum;
    wire Cout;

    Lab2_4_bit_CLA M1(Sum, Cout, A, B, Cin);

    initial begin
    $dumpfile("Lab2_4_bit_CLA.vcd");
    $dumpvars;
            A = 4'b1101; B = 4'b0101; Cin = 0;
        #50 A = 4'b1100; B = 4'b1000; Cin = 1;
        #50 A = 4'b0101; B = 4'b1101; Cin = 0;
        #50 A = 4'b1000; B = 4'b1100; Cin = 1;
        #50 A = 4'b0101; B = 4'b0101; Cin = 0;
        #50 A = 4'b1011; B = 4'b1011; Cin = 1;
        #50 A = 4'b1111; B = 4'b1111; Cin = 1;
        #50 A = 4'b1111; B = 4'b0000; Cin = 1;

    end 

    initial #400 $finish;
endmodule

Lab2/Lab2_4_bit_CLA.vcd
$date
	Mon May 25 23:34:16 2020
$end
$version
	Icarus Verilog
$end
$timescale
	1s
$end
$scope module t_Lab2_4_bit_CLA $end
$var wire 4 ! Sum [3:0] $end
$var wire 1 " Cout $end
$var reg 4 # A [3:0] $end
$var reg 4 $ B [3:0] $end
$var reg 1 % Cin $end
$scope module M1 $end
$var wire 4 & A [3:0] $end
$var wire 4 ' B [3:0] $end
$var wire 1 % Cin $end
$var wire 4 ( Sum [3:0] $end
$var wire 4 ) P [3:0] $end
$var wire 4 * G [3:0] $end
$var wire 1 " Cout $end
$var wire 4 + C [4:1] $end
$scope module M2 $end
$var wire 1 % C0 $end
$var wire 4 , G [3:0] $end
$var wire 4 - P [3:0] $end
$var wire 4 . C [4:1] $end
$upscope $end
$upscope $end
$upscope $end
$enddefinitions $end
#0
$dumpvars
b1101 .
b1000 -
b101 ,
b1101 +
b101 *
b1000 )
b10 (
b101 '
b1101 &
0%
b101 $
b1101 #
1"
b10 !
$end
#50
b1000 +
b1000 .
b100 )
b100 -
b1000 *
b1000 ,
b101 !
b101 (
1%
b1000 $
b1000 '
b1100 #
b1100 &
#100
1"
b1101 +
b1101 .
b101 *
b101 ,
b1000 )
b1000 -
b10 !
b10 (
0%
b1101 $
b1101 '
b101 #
b101 &
#150
b1000 +
b1000 .
b1000 *
b1000 ,
b100 )
b100 -
b101 !
b101 (
1%
b1100 $
b1100 '
b1000 #
b1000 &
#200
0"
b101 +
b101 .
b0 )
b0 -
b101 *
b101 ,
b1010 !
b1010 (
0%
b101 $
b101 '
b101 #
b101 &
#250
1"
b1011 +
b1011 .
b1011 *
b1011 ,
b111 !
b111 (
1%
b1011 $
b1011 '
b1011 #
b1011 &
#300
b1111 !
b1111 (
b1111 +
b1111 .
b1111 *
b1111 ,
b1111 $
b1111 '
b1111 #
b1111 &
#350
1"
b1111 +
b1111 .
b0 !
b0 (
b0 *
b0 ,
b1111 )
b1111 -
b0 $
b0 '
