Lab2/Lab2_0719819_游心瑜/Lab2_CLG_dataflow.v
module Lab2_CLG_dataflow(C, P, G, C0);

    output [4:1] C;
    input [3:0] P, G;
    input C0;

    assign C[1] = (P[0] & C0) | G[0];
    assign C[2] = (P[0] & C0 & P[1]) | (P[1] & G[0]) | G[1];
    assign C[3] = (P[0] & C0 & P[1] & P[2]) | (P[1] & G[0] & P[2]) | (G[1] & P[2]) | G[2];
    assign C[4] = (P[0] & C0 & P[1] & P[2] & P[3]) | (P[1] & G[0] & P[2] & P[3]) | (G[1] & P[2] & P[3]) | (G[2] & P[3]) | G[3];

endmodule

Lab2/Lab2_0719819_游心瑜/Lab2_4_bit_BLS.v
module Lab2_4_bit_BLS(Diff, Bout, X, Y, Bin);

    output [3:0] Diff;
    output Bout;
    input [3:0] X, Y;
    input Bin;

    wire [3:0] P, G;
    wire [4:1] B;

    assign P = ~(X^Y);
    assign G = (~X) & Y;
    Lab2_CLG_dataflow M2(B, P, G, Bin);

    assign Diff[0] = ~P[0] ^ Bin;
    assign Diff[1] = ~P[1] ^ B[1];
    assign Diff[2] = ~P[2] ^ B[2];
    assign Diff[3] = ~P[3] ^ B[3];
    assign Bout = B[4];

endmodule

Lab2/Lab2_0719819_游心瑜/t_Lab2_4_bit_BLS.v
module    t_Lab2_4_bit_BLS;

    reg [3:0] X, Y;
    reg Bin;

    wire [3:0] Diff;
    wire Bout;

    Lab2_4_bit_BLS M1(Diff, Bout, X, Y, Bin);

    initial begin
    $dumpfile("Lab2_4_bit_BLS.vcd");
    $dumpvars;
            X = 4'b1101; Y = 4'b0101; Bin = 0;
        #50 X = 4'b1100; Y = 4'b1000; Bin = 1;
        #50 X = 4'b0101; Y = 4'b1101; Bin = 0;
        #50 X = 4'b1000; Y = 4'b1100; Bin = 1;
        #50 X = 4'b0101; Y = 4'b0101; Bin = 0;
        #50 X = 4'b1011; Y = 4'b1011; Bin = 1;
        #50 X = 4'b0000; Y = 4'b1111; Bin = 0;
        #50 X = 4'b0000; Y = 4'b1111; Bin = 1;

    end 

    initial #400 $finish;
endmodule

Lab2/Lab2_4_bit_BLS.vcd
$date
	Mon May 25 23:41:23 2020
$end
$version
	Icarus Verilog
$end
$timescale
	1s
$end
$scope module t_Lab2_4_bit_BLS $end
$var wire 4 ! Diff [3:0] $end
$var wire 1 " Bout $end
$var reg 1 # Bin $end
$var reg 4 $ X [3:0] $end
$var reg 4 % Y [3:0] $end
$scope module M1 $end
$var wire 1 # Bin $end
$var wire 4 & G [3:0] $end
$var wire 4 ' P [3:0] $end
$var wire 4 ( X [3:0] $end
$var wire 4 ) Y [3:0] $end
$var wire 4 * Diff [3:0] $end
$var wire 1 " Bout $end
$var wire 4 + B [4:1] $end
$scope module M2 $end
$var wire 1 # C0 $end
$var wire 4 , G [3:0] $end
$var wire 4 - P [3:0] $end
$var wire 4 . C [4:1] $end
$upscope $end
$upscope $end
$upscope $end
$enddefinitions $end
#0
$dumpvars
b0 .
b111 -
b0 ,
b0 +
b1000 *
b101 )
b1101 (
b111 '
b0 &
b101 %
b1101 $
0#
0"
b1000 !
$end
#50
b11 +
b11 .
b1011 '
b1011 -
b11 !
b11 *
1#
b1000 %
b1000 )
b1100 $
b1100 (
#100
1"
b1000 +
b1000 .
b111 '
b111 -
b1000 !
b1000 *
b1000 &
b1000 ,
0#
b1101 %
b1101 )
b101 $
b101 (
#150
1"
b1111 +
b1111 .
b1011 '
b1011 -
b1011 !
b1011 *
b100 &
b100 ,
1#
b1100 %
b1100 )
b1000 $
b1000 (
#200
0"
b0 +
b0 .
b1111 '
b1111 -
b0 !
b0 *
b0 &
b0 ,
0#
b101 %
b101 )
b101 $
b101 (
#250
1"
b1111 +
b1111 .
b1111 !
b1111 *
1#
b1011 %
b1011 )
b1011 $
b1011 (
#300
b0 '
b0 -
b1 !
b1 *
b1111 &
b1111 ,
0#
b1111 %
b1111 )
b0 $
b0 (
#350
b0 !
b0 *
1#
